[
  {
    "item": {
      "title": "Preact CLI",
      "framework": "Preact",
      "firstRender": 412
    },
    "json": {
      "items": [
        {
          "url": "/bundle.js",
          "totalBytes": 4733,
          "totalKb": "5 KB",
          "totalMs": "20ms",
          "parsed": {
            "root": "/",
            "dir": "/",
            "base": "bundle.js",
            "ext": ".js",
            "name": "bundle"
          }
        }
      ],
      "total": {
        "bytes": 4733,
        "pretty": "4.73 kB"
      }
    },
    "img": "img/preact.png"
  },
  {
    "item": {
      "title": "Create Inferno App",
      "framework": "Inferno",
      "firstRender": 737
    },
    "json": {
      "items": [
        {
          "url": "…js/main.84098ec8.js",
          "totalBytes": 17472,
          "totalKb": "17 KB",
          "totalMs": "70ms",
          "parsed": {
            "root": "",
            "dir": "…js",
            "base": "main.84098ec8.js",
            "ext": ".js",
            "name": "main.84098ec8"
          }
        }
      ],
      "total": {
        "bytes": 17472,
        "pretty": "17.5 kB"
      }
    },
    "img": "img/inferno.png"
  },
  {
    "item": {
      "title": "Ember CLI",
      "framework": "Glimmer",
      "firstRender": 1000
    },
    "json": {
      "items": [
        {
          "url": "/app-3f14cb2….js",
          "totalBytes": 34673,
          "totalKb": "34 KB",
          "totalMs": "160ms",
          "parsed": {
            "root": "/",
            "dir": "/",
            "base": "app-3f14cb2….js",
            "ext": ".js",
            "name": "app-3f14cb2…"
          }
        }
      ],
      "total": {
        "bytes": 34673,
        "pretty": "34.7 kB"
      }
    },
    "img": "img/glimmer.png"
  },
  {
    "item": {
      "title": "Vue CLI",
      "framework": "Vue",
      "firstRender": 840
    },
    "json": {
      "items": [
        {
          "url": "…js/vendor.94202f7….js",
          "totalBytes": 36628,
          "totalKb": "36 KB",
          "totalMs": "170ms",
          "parsed": {
            "root": "",
            "dir": "…js",
            "base": "vendor.94202f7….js",
            "ext": ".js",
            "name": "vendor.94202f7…"
          }
        },
        {
          "url": "…js/app.e592187….js",
          "totalBytes": 8087,
          "totalKb": "8 KB",
          "totalMs": "40ms",
          "parsed": {
            "root": "",
            "dir": "…js",
            "base": "app.e592187….js",
            "ext": ".js",
            "name": "app.e592187…"
          }
        },
        {
          "url": "…js/manifest.1a71ed3….js",
          "totalBytes": 1188,
          "totalKb": "1 KB",
          "totalMs": "10ms",
          "parsed": {
            "root": "",
            "dir": "…js",
            "base": "manifest.1a71ed3….js",
            "ext": ".js",
            "name": "manifest.1a71ed3…"
          }
        }
      ],
      "total": {
        "bytes": 45903,
        "pretty": "45.9 kB"
      }
    },
    "img": "img/vue.png"
  },
  {
    "item": {
      "title": "Create React App",
      "framework": "React",
      "firstRender": 770
    },
    "json": {
      "items": [
        {
          "url": "…js/main.4268d1ce.js",
          "totalBytes": 47727,
          "totalKb": "47 KB",
          "totalMs": "210ms",
          "parsed": {
            "root": "",
            "dir": "…js",
            "base": "main.4268d1ce.js",
            "ext": ".js",
            "name": "main.4268d1ce"
          }
        }
      ],
      "total": {
        "bytes": 47727,
        "pretty": "47.7 kB"
      }
    },
    "img": "img/cra.png"
  },
  {
    "item": {
      "title": "Angular CLI",
      "framework": "Angular 2",
      "firstRender": 1500
    },
    "json": {
      "items": [
        {
          "url": "/vendor.f36e67a….bundle.js",
          "totalBytes": 71552,
          "totalKb": "70 KB",
          "totalMs": "330ms",
          "parsed": {
            "root": "/",
            "dir": "/",
            "base": "vendor.f36e67a….bundle.js",
            "ext": ".js",
            "name": "vendor.f36e67a….bundle"
          }
        },
        {
          "url": "/polyfills.2d45a4c….bundle.js",
          "totalBytes": 19396,
          "totalKb": "19 KB",
          "totalMs": "90ms",
          "parsed": {
            "root": "/",
            "dir": "/",
            "base": "polyfills.2d45a4c….bundle.js",
            "ext": ".js",
            "name": "polyfills.2d45a4c….bundle"
          }
        },
        {
          "url": "/main.34c7a68….bundle.js",
          "totalBytes": 2531,
          "totalKb": "2 KB",
          "totalMs": "10ms",
          "parsed": {
            "root": "/",
            "dir": "/",
            "base": "main.34c7a68….bundle.js",
            "ext": ".js",
            "name": "main.34c7a68….bundle"
          }
        },
        {
          "url": "/inline.1a4182d….bundle.js",
          "totalBytes": 1155,
          "totalKb": "1 KB",
          "totalMs": "10ms",
          "parsed": {
            "root": "/",
            "dir": "/",
            "base": "inline.1a4182d….bundle.js",
            "ext": ".js",
            "name": "inline.1a4182d….bundle"
          }
        }
      ],
      "total": {
        "bytes": 94634,
        "pretty": "94.6 kB"
      }
    },
    "img": "img/ng.png"
  },
  {
    "item": {
      "title": "Ember CLI",
      "framework": "Ember",
      "firstRender": 4200
    },
    "json": {
      "items": [
        {
          "url": "…assets/vendor-762ee20….js",
          "totalBytes": 203077,
          "totalKb": "198 KB",
          "totalMs": "960ms",
          "parsed": {
            "root": "",
            "dir": "…assets",
            "base": "vendor-762ee20….js",
            "ext": ".js",
            "name": "vendor-762ee20…"
          }
        },
        {
          "url": "…assets/ember-app-3e61472….js",
          "totalBytes": 1769,
          "totalKb": "2 KB",
          "totalMs": "10ms",
          "parsed": {
            "root": "",
            "dir": "…assets",
            "base": "ember-app-3e61472….js",
            "ext": ".js",
            "name": "ember-app-3e61472…"
          }
        }
      ],
      "total": {
        "bytes": 204846,
        "pretty": "205 kB"
      }
    },
    "img": "img/ember.png"
  }
]